ani_scrapy/__init__.py
ani_scrapy/py.typed
ani_scrapy/async_api/__init__.py
ani_scrapy/async_api/base.py
ani_scrapy/async_api/browser.py
ani_scrapy/async_api/scrapers/animeflv/file_link.py
ani_scrapy/async_api/scrapers/animeflv/scraper.py
ani_scrapy/async_api/scrapers/animeflv/tab_link.py
ani_scrapy/async_api/scrapers/animeflv/utils.py
ani_scrapy/async_api/scrapers/jkanime/file_link.py
ani_scrapy/async_api/scrapers/jkanime/scraper.py
ani_scrapy/core/__init__.py
ani_scrapy/core/base.py
ani_scrapy/core/exceptions.py
ani_scrapy/core/schemas.py
ani_scrapy/core/constants/animeflv.py
ani_scrapy/core/constants/general.py
ani_scrapy/core/constants/jkanime.py
ani_scrapy/core/utils/animeflv.py
ani_scrapy/core/utils/general.py
ani_scrapy/sync_api/__init__.py
ani_scrapy/sync_api/base.py
ani_scrapy/sync_api/browser.py
ani_scrapy/sync_api/scrapers/animeflv/file_link.py
ani_scrapy/sync_api/scrapers/animeflv/scraper.py
ani_scrapy/sync_api/scrapers/animeflv/tab_link.py
ani_scrapy/sync_api/scrapers/animeflv/utils.py
ani_scrapy/sync_api/scrapers/jkanime/file_link.py
ani_scrapy/sync_api/scrapers/jkanime/scraper.py
ani_scrapy-0.1.23.dist-info/licenses/LICENSE
ani_scrapy-0.1.23.dist-info/METADATA
ani_scrapy-0.1.23.dist-info/WHEEL
ani_scrapy-0.1.23.dist-info/top_level.txt
ani_scrapy-0.1.23.dist-info/RECORD
