Metadata-Version: 2.4
Name: ani-scrapy
Version: 0.1.23
Summary: Python library for scraping anime websites, currently supporting AnimeFLV and JKAnime.
Author-email: "github:ElPitagoras14" <jonfrgar@espol.edu.ec>
License: MIT
Project-URL: Homepage, https://github.com/ElPitagoras14/ani-scrapy
Project-URL: Repository, https://github.com/ElPitagoras14/ani-scrapy
Keywords: anime,scraping,playwright,async,python
Classifier: Programming Language :: Python :: 3
Classifier: License :: OSI Approved :: MIT License
Classifier: Operating System :: OS Independent
Classifier: Topic :: Internet :: WWW/HTTP
Classifier: Topic :: Software Development :: Libraries :: Python Modules
Requires-Python: >=3.10.14
License-File: LICENSE
Requires-Dist: aiohttp>=3.13.0
Requires-Dist: beautifulsoup4>=4.14.2
Requires-Dist: cloudscraper>=1.2.71
Requires-Dist: curl-cffi>=0.13.0
Requires-Dist: loguru>=0.7.3
Requires-Dist: lxml>=6.0.2
Requires-Dist: playwright>=1.55.0
Requires-Dist: playwright-stealth>=2.0.0
Requires-Dist: requests>=2.32.5
Dynamic: license-file
